datatask/__init__.py
datatask/datatask.py
datatask-0.3.0.dist-info/LICENSE
datatask-0.3.0.dist-info/METADATA
datatask-0.3.0.dist-info/WHEEL
datatask-0.3.0.dist-info/top_level.txt
datatask-0.3.0.dist-info/RECORD
